{
  "summary": {
    "total_apps": 770,
    "total_countries": 7,
    "total_industries": 3,
    "avg_rating": 4.33,
    "last_updated": "2026-07-05T06:16:52.188782Z"
  },
  "top_movers": [
    {
      "app_id": "com.fastringgit.official",
      "country_code": "MY",
      "store": "google_play",
      "timestamp": "2026-07-05T06:16:52.180011Z",
      "rank": 4,
      "rating": 4.28,
      "reviews": 1620,
      "min_installs": 150044,
      "installs_str": "100,000+",
      "dau_estimate": 1800,
      "ad_spend_intensity": 33.5,
      "rank_change": 2,
      "rating_change": 0.16,
      "reviews_change": 20,
      "installs_change": 0,
      "installs_growth": 0.0,
      "dau_change": 300,
      "is_new": false,
      "app_name": "FastRinggit",
      "icon_url": "https://play-lh.googleusercontent.com/UU-dKYFPYJRmly86XgujtkT_EvY_zyRIoha7POfXCB6mO0wJwPGKhL4z-FdDMoSXQTBcM7foDmkX9-GWl6eULg",
      "developer": "FastRinggit SDN BHD",
      "industry": "credit",
      "industry_name": "信贷",
      "country_name": "马来西亚"
    },
    {
      "app_id": "asia.versa.cms",
      "country_code": "MY",
      "store": "google_play",
      "timestamp": "2026-07-05T06:16:52.180011Z",
      "rank": 20,
      "rating": 4.71,
      "reviews": 5881,
      "min_installs": 396046,
      "installs_str": "100,000+",
      "dau_estimate": 5940,
      "ad_spend_intensity": 24.7,
      "rank_change": 2,
      "rating_change": 0.0,
      "reviews_change": 5,
      "installs_change": 0,
      "installs_growth": 0.0,
      "dau_change": 0,
      "is_new": false,
      "app_name": "Versa: Save. Invest. Grow.",
      "icon_url": "https://play-lh.googleusercontent.com/veHdUFY0u9ldzxP2R-GmT6OSjsNK_00-5reUEY3rnZLBagcNychXWhhaJSXqH3zhTsf_0yBlRZ7ohsuogo9jsw",
      "developer": "Versa Asia Sdn Bhd",
      "industry": "finance",
      "industry_name": "理财",
      "country_name": "马来西亚"
    },
    {
      "app_id": "com.wings.easyborrow.ph",
      "country_code": "PH",
      "store": "google_play",
      "timestamp": "2026-07-05T06:16:52.180011Z",
      "rank": 20,
      "rating": 4.6,
      "reviews": 72123,
      "min_installs": 683099,
      "installs_str": "500,000+",
      "dau_estimate": 11271,
      "ad_spend_intensity": 26.6,
      "rank_change": 1,
      "rating_change": 0.0,
      "reviews_change": 378,
      "installs_change": 0,
      "installs_growth": 0.0,
      "dau_change": 0,
      "is_new": false,
      "app_name": "EASY BORROW",
      "icon_url": "https://play-lh.googleusercontent.com/-kGVJieKujiX4HdslTBh2HmiElv-RyIHhv6qwRy7qPRM_nIuAAFOqTiDbTFPCC5cZDsFKFdcR4xAmjBHP0sucA",
      "developer": "Wing of Integrity Lending Corp.",
      "industry": "credit",
      "industry_name": "信贷",
      "country_name": "菲律宾"
    },
    {
      "app_id": "com.waleefinancialservices.hakeem",
      "country_code": "PK",
      "store": "google_play",
      "timestamp": "2026-07-05T06:16:52.180011Z",
      "rank": 9,
      "rating": 4.08,
      "reviews": 11405,
      "min_installs": 2138780,
      "installs_str": "1,000,000+",
      "dau_estimate": 23526,
      "ad_spend_intensity": 29.8,
      "rank_change": 1,
      "rating_change": 0.0,
      "reviews_change": 5,
      "installs_change": 0,
      "installs_growth": 0.0,
      "dau_change": 0,
      "is_new": false,
      "app_name": "Hakeem Easy Finance",
      "icon_url": "https://play-lh.googleusercontent.com/9k4Sp1Pw4Py9jhzamG79IwTSpueJZ2eA-6PfnPjqafF8aWY8oYJW36IdkGL5sqj5gmfkjcXtNxHD6G4bzLN_oQ",
      "developer": "Walee Financial Services (Private) Limited",
      "industry": "credit",
      "industry_name": "信贷",
      "country_name": "巴基斯坦"
    },
    {
      "app_id": "com.finja.business",
      "country_code": "PK",
      "store": "google_play",
      "timestamp": "2026-07-05T06:16:52.180011Z",
      "rank": 22,
      "rating": 4.05,
      "reviews": 2487,
      "min_installs": 380810,
      "installs_str": "100,000+",
      "dau_estimate": 3808,
      "ad_spend_intensity": 20.3,
      "rank_change": 1,
      "rating_change": 0.0,
      "reviews_change": 2,
      "installs_change": 0,
      "installs_growth": 0.0,
      "dau_change": 0,
      "is_new": false,
      "app_name": "Finja",
      "icon_url": "https://play-lh.googleusercontent.com/75ZDjPXuUlNkjHea3LtaS21ZAOkK4y5nMbXYIkSHuVPBf2CA4hWtQUenS3x-ppXoAorpNWvPeRCX0MuPpNC8VQ",
      "developer": "OPay Digital Services Limited",
      "industry": "credit",
      "industry_name": "信贷",
      "country_name": "巴基斯坦"
    },
    {
      "app_id": "com.maybank.bankpublic.jpmorgan",
      "country_code": "MY",
      "store": "google_play",
      "timestamp": "2026-07-05T06:16:52.180011Z",
      "rank": 6,
      "rating": 4.59,
      "reviews": 1107,
      "min_installs": 10481,
      "installs_str": "10,000+",
      "dau_estimate": 157,
      "ad_spend_intensity": 29.8,
      "rank_change": 1,
      "rating_change": 0.03,
      "reviews_change": 13,
      "installs_change": 0,
      "installs_growth": 0.0,
      "dau_change": 0,
      "is_new": false,
      "app_name": "SpeedyAid",
      "icon_url": "https://play-lh.googleusercontent.com/IlvYy4wK7vP-5rF-bjeS9Dtr4WnQOQDDwZqR_dSwAXmd1DCJENvSu8crRJCk1oUeVtb2oFV_OayIpIvdz2_8KA",
      "developer": "Powered by KHAZANA FINANCIAL SERVICES LIMITED",
      "industry": "credit",
      "industry_name": "信贷",
      "country_name": "马来西亚"
    },
    {
      "app_id": "com.adacashmobile",
      "country_code": "MY",
      "store": "google_play",
      "timestamp": "2026-07-05T06:16:52.180011Z",
      "rank": 13,
      "rating": 4.39,
      "reviews": 4984,
      "min_installs": 429268,
      "installs_str": "100,000+",
      "dau_estimate": 5151,
      "ad_spend_intensity": 24.7,
      "rank_change": 1,
      "rating_change": 0.0,
      "reviews_change": 11,
      "installs_change": 0,
      "installs_growth": 0.0,
      "dau_change": 0,
      "is_new": false,
      "app_name": "Adacash",
      "icon_url": "https://play-lh.googleusercontent.com/CeQPCsqur7ROCd5FZBp7V5hmwQE32wEpg0nX1fmoxc0vsfOnf_ees6FaFDr9HE2WeI3xysSdxT_7Jf-Gsj5BWtw",
      "developer": "Rock Wing",
      "industry": "credit",
      "industry_name": "信贷",
      "country_name": "马来西亚"
    },
    {
      "app_id": "id.fdr.app",
      "country_code": "MY",
      "store": "google_play",
      "timestamp": "2026-07-05T06:16:52.180011Z",
      "rank": 23,
      "rating": 4.3,
      "reviews": 286,
      "min_installs": 29925,
      "installs_str": "10,000+",
      "dau_estimate": 359,
      "ad_spend_intensity": 20.0,
      "rank_change": 1,
      "rating_change": 0.17,
      "reviews_change": 11,
      "installs_change": 0,
      "installs_growth": 0.0,
      "dau_change": 60,
      "is_new": false,
      "app_name": "Fundora",
      "icon_url": "https://play-lh.googleusercontent.com/xOQhNgVMUZuDjDpBYuByiVDxzwIHgHlfns-wRFuXWaldayk0o-Qz1xa3NPnsCUx8nP4YQ8vkl6k2PLmqtFtb",
      "developer": "Fundora Finance Industry",
      "industry": "credit",
      "industry_name": "信贷",
      "country_name": "马来西亚"
    },
    {
      "app_id": "com.optipay.littlecash",
      "country_code": "AU",
      "store": "google_play",
      "timestamp": "2026-07-05T06:16:52.180011Z",
      "rank": 5,
      "rating": 4.29,
      "reviews": 104909,
      "min_installs": 1240024,
      "installs_str": "1,000,000+",
      "dau_estimate": 19344,
      "ad_spend_intensity": 32.3,
      "rank_change": 1,
      "rating_change": 0.02,
      "reviews_change": 24,
      "installs_change": 0,
      "installs_growth": 0.0,
      "dau_change": 0,
      "is_new": false,
      "app_name": "Little Cash - Mobile Loans",
      "icon_url": "https://play-lh.googleusercontent.com/2bCaBF1Lb5eJkhmZ9KNMg7ww-PEvyk7TXKfTxSr46_M1tLKhZeTPZJoq5EQ4NFa1c3g",
      "developer": "Optipay Limited",
      "industry": "credit",
      "industry_name": "信贷",
      "country_name": "英国"
    },
    {
      "app_id": "au.com.credit24",
      "country_code": "AU",
      "store": "google_play",
      "timestamp": "2026-07-05T06:16:52.180011Z",
      "rank": 20,
      "rating": 4.1,
      "reviews": 29,
      "min_installs": 19823,
      "installs_str": "10,000+",
      "dau_estimate": 198,
      "ad_spend_intensity": 31.5,
      "rank_change": 1,
      "rating_change": 0.0,
      "reviews_change": 0,
      "installs_change": 0,
      "installs_growth": 0.0,
      "dau_change": 0,
      "is_new": false,
      "app_name": "Credit24",
      "icon_url": "https://play-lh.googleusercontent.com/xPHCeCrIItP-InPcSJoXpmk-VSjlLdVj_f1-XS5iIgVM-5yTI-5OrEt4QJDiqzsTvhw_SeeFGg45GrTHUGj0",
      "developer": "IPF Digital",
      "industry": "credit",
      "industry_name": "信贷",
      "country_name": "澳大利亚"
    }
  ],
  "industry_distribution": {
    "credit": 453,
    "finance": 286,
    "insurance": 31
  },
  "country_distribution": {
    "PH": 64,
    "ID": 48,
    "PK": 106,
    "MY": 104,
    "AU": 137,
    "GB": 150,
    "MX": 161
  }
}