{
  "summary": {
    "total_apps": 760,
    "total_countries": 7,
    "total_industries": 3,
    "avg_rating": 4.35,
    "last_updated": "2026-06-21T07:02:35.836177Z"
  },
  "top_movers": [
    {
      "app_id": "com.wagetap",
      "country_code": "AU",
      "store": "google_play",
      "timestamp": "2026-06-21T07:02:35.829300Z",
      "rank": 18,
      "rating": 4.81,
      "reviews": 12199,
      "min_installs": 367026,
      "installs_str": "100,000+",
      "dau_estimate": 6055,
      "ad_spend_intensity": 28.2,
      "rank_change": 5,
      "rating_change": 0.0,
      "reviews_change": 18,
      "installs_change": 0,
      "installs_growth": 0.0,
      "dau_change": 0,
      "is_new": false,
      "app_name": "Wagetap: Instant Cash Advance",
      "icon_url": "https://play-lh.googleusercontent.com/kmZdfO42dWRTCSAQ2V2HXX5gjazpANsQnTP0EoWFOBQPzB2jBX6wl33ZdCmDj2eN9CZzTJSGLMC2xiZwe2NAMdI",
      "developer": "Digital Services Australia V Pty Ltd",
      "industry": "credit",
      "industry_name": "信贷",
      "country_name": "澳大利亚"
    },
    {
      "app_id": "com.alvos.app",
      "country_code": "MX",
      "store": "google_play",
      "timestamp": "2026-06-21T07:02:35.829300Z",
      "rank": 15,
      "rating": 4.73,
      "reviews": 49671,
      "min_installs": 1258276,
      "installs_str": "1.000.000+",
      "dau_estimate": 20761,
      "ad_spend_intensity": 36.5,
      "rank_change": 5,
      "rating_change": 0.0,
      "reviews_change": 156,
      "installs_change": 0,
      "installs_growth": 0.0,
      "dau_change": 0,
      "is_new": false,
      "app_name": "Préstamos de Dinero - ALVOS",
      "icon_url": "https://play-lh.googleusercontent.com/5-KmVnU4xE6VhE8pS3rDVgxdo6t9HpzLM7Oo8ZkBb7nL8wcvIgvMSp5ch1T8_ZZb-LIeyiAHyvwRBjl3zF7xdX4",
      "developer": "ALVOS",
      "industry": "finance",
      "industry_name": "理财",
      "country_name": "墨西哥"
    },
    {
      "app_id": "com.newday.newpay",
      "country_code": "GB",
      "store": "google_play",
      "timestamp": "2026-06-21T07:02:35.829300Z",
      "rank": 23,
      "rating": 4.26,
      "reviews": 434,
      "min_installs": 81813,
      "installs_str": "50,000+",
      "dau_estimate": 981,
      "ad_spend_intensity": 27.8,
      "rank_change": 4,
      "rating_change": 0.0,
      "reviews_change": 0,
      "installs_change": 0,
      "installs_growth": 0.0,
      "dau_change": 0,
      "is_new": false,
      "app_name": "Newpay",
      "icon_url": "https://play-lh.googleusercontent.com/5MztdlrsJYr_bLDoNr-yzWVkTUMXgEBynMV_aGFRXpfe6EA8tzjxQ1sVdmATe_VCnmubAXZ0MKyFCzJjhVTS",
      "developer": "NewDay Ltd",
      "industry": "credit",
      "industry_name": "信贷",
      "country_name": "英国"
    },
    {
      "app_id": "co.uk.getmondo",
      "country_code": "GB",
      "store": "google_play",
      "timestamp": "2026-06-21T07:02:35.829300Z",
      "rank": 14,
      "rating": 4.78,
      "reviews": 176230,
      "min_installs": 13392477,
      "installs_str": "10,000,000+",
      "dau_estimate": 261153,
      "ad_spend_intensity": 30.5,
      "rank_change": 3,
      "rating_change": 0.0,
      "reviews_change": 76,
      "installs_change": 7845,
      "installs_growth": 0.06,
      "dau_change": 153,
      "is_new": false,
      "app_name": "Monzo Bank - Mobile Banking",
      "icon_url": "https://play-lh.googleusercontent.com/2S7rGRzx4bBnN0M1vGHIDBGI8SnSg2G_dShvpNjsDqdffWrGd99icCDXCnM1EVF-vy43gFjKjimZWGQ741UT_A",
      "developer": "Monzo",
      "industry": "finance",
      "industry_name": "理财",
      "country_name": "英国"
    },
    {
      "app_id": "com.loan.cash.credit.easy.kilat.cepat.pinjam.uang.dana.rupiah",
      "country_code": "ID",
      "store": "google_play",
      "timestamp": "2026-06-21T07:02:35.829300Z",
      "rank": 1,
      "rating": 4.61,
      "reviews": 1603594,
      "min_installs": 38646910,
      "installs_str": "10.000.000+",
      "dau_estimate": 753614,
      "ad_spend_intensity": 35.9,
      "rank_change": 2,
      "rating_change": 0.0,
      "reviews_change": 216,
      "installs_change": 42605,
      "installs_growth": 0.11,
      "dau_change": 831,
      "is_new": false,
      "app_name": "RupiahCepat - Pinjaman Dana",
      "icon_url": "https://play-lh.googleusercontent.com/O3GVv7kfzKr3UbdmKfieb5i3LvXI3cvcf0Igshn1aN80fsBPQgKYXoYfZifATzwVWLMmkVS9NwJ1e3RByoAc1ds",
      "developer": "PT KreditUtamaFintechIndonesia",
      "industry": "credit",
      "industry_name": "信贷",
      "country_name": "印尼"
    },
    {
      "app_id": "com.stanfordtek.pinjamduit",
      "country_code": "ID",
      "store": "google_play",
      "timestamp": "2026-06-21T07:02:35.829300Z",
      "rank": 24,
      "rating": 4.62,
      "reviews": 2444239,
      "min_installs": 25063046,
      "installs_str": "10.000.000+",
      "dau_estimate": 488729,
      "ad_spend_intensity": 22.2,
      "rank_change": 2,
      "rating_change": 0.0,
      "reviews_change": 723,
      "installs_change": 0,
      "installs_growth": 0.0,
      "dau_change": 0,
      "is_new": false,
      "app_name": "PinjamDuit - Pinjaman Daring",
      "icon_url": "https://play-lh.googleusercontent.com/YzZRVfZS0rlh32uQfel6Hvp0yB0Olk-GcJYKbVQ6bPRFs9tet_2IuWP-bfPh_HtTDZPbbU8NaR3ScAyPbISxxw",
      "developer": "PT Stanford Teknologi Indonesia",
      "industry": "credit",
      "industry_name": "信贷",
      "country_name": "印尼"
    },
    {
      "app_id": "com.pinjamango",
      "country_code": "ID",
      "store": "google_play",
      "timestamp": "2026-06-21T07:02:35.829300Z",
      "rank": 27,
      "rating": 4.53,
      "reviews": 642114,
      "min_installs": 9200330,
      "installs_str": "5.000.000+",
      "dau_estimate": 179406,
      "ad_spend_intensity": 23.1,
      "rank_change": 2,
      "rating_change": 0.0,
      "reviews_change": 403,
      "installs_change": 0,
      "installs_growth": 0.0,
      "dau_change": 0,
      "is_new": false,
      "app_name": "PinjamanGo-Pinjaman Uang Cepat",
      "icon_url": "https://play-lh.googleusercontent.com/yhJn6zijZ0aNfRttWwnruoLxpN_hSzLB6M3KZqlQSxoPcKqElKCb2XuUbkpdMrYoGBN-jNCR37LisX0IRjvY",
      "developer": "PT. Dana Pinjaman Inklusif",
      "industry": "credit",
      "industry_name": "信贷",
      "country_name": "印尼"
    },
    {
      "app_id": "com.waleefinancialservices.hakeem",
      "country_code": "PK",
      "store": "google_play",
      "timestamp": "2026-06-21T07:02:35.829300Z",
      "rank": 10,
      "rating": 4.07,
      "reviews": 11264,
      "min_installs": 2062023,
      "installs_str": "1,000,000+",
      "dau_estimate": 22682,
      "ad_spend_intensity": 28.6,
      "rank_change": 2,
      "rating_change": 0.01,
      "reviews_change": 16,
      "installs_change": 0,
      "installs_growth": 0.0,
      "dau_change": 0,
      "is_new": false,
      "app_name": "Hakeem Easy Finance",
      "icon_url": "https://play-lh.googleusercontent.com/9k4Sp1Pw4Py9jhzamG79IwTSpueJZ2eA-6PfnPjqafF8aWY8oYJW36IdkGL5sqj5gmfkjcXtNxHD6G4bzLN_oQ",
      "developer": "Walee Financial Services (Private) Limited",
      "industry": "credit",
      "industry_name": "信贷",
      "country_name": "巴基斯坦"
    },
    {
      "app_id": "com.personal.loan.loanlado.credit.easy.jazz.online.cash",
      "country_code": "PK",
      "store": "google_play",
      "timestamp": "2026-06-21T07:02:35.829300Z",
      "rank": 11,
      "rating": 4.02,
      "reviews": 16340,
      "min_installs": 379208,
      "installs_str": "100,000+",
      "dau_estimate": 4171,
      "ad_spend_intensity": 30.5,
      "rank_change": 2,
      "rating_change": 0.0,
      "reviews_change": -1,
      "installs_change": 0,
      "installs_growth": 0.0,
      "dau_change": 0,
      "is_new": false,
      "app_name": "LoanLado - Easy Personal Loan",
      "icon_url": "https://play-lh.googleusercontent.com/qhj8yVTX0tGz1vt0eUcxvHWJtTAmOq5SAN8CpsTl7j2QsG_mXZ52lacBVmBE07MpU0KY5lt_xa97bTTZ3sYqLg",
      "developer": "EASY FINANCE",
      "industry": "credit",
      "industry_name": "信贷",
      "country_name": "巴基斯坦"
    },
    {
      "app_id": "my.wkash.app",
      "country_code": "MY",
      "store": "google_play",
      "timestamp": "2026-06-21T07:02:35.829300Z",
      "rank": 5,
      "rating": 4.36,
      "reviews": 414,
      "min_installs": 30245,
      "installs_str": "10,000+",
      "dau_estimate": 362,
      "ad_spend_intensity": 33.6,
      "rank_change": 2,
      "rating_change": -0.04,
      "reviews_change": 6,
      "installs_change": 0,
      "installs_growth": 0.0,
      "dau_change": 0,
      "is_new": false,
      "app_name": "WantKash",
      "icon_url": "https://play-lh.googleusercontent.com/mvV4DdYodmdwyPU9WhptztMRM15dbsPT2RxZXhH_us_1laqZ24uhtF8QtvBz8diVZkhUnJKHPbFGKiPu11ZZv9I",
      "developer": "WantKash Finance",
      "industry": "credit",
      "industry_name": "信贷",
      "country_name": "马来西亚"
    }
  ],
  "industry_distribution": {
    "credit": 450,
    "finance": 280,
    "insurance": 30
  },
  "country_distribution": {
    "PH": 64,
    "ID": 47,
    "PK": 105,
    "MY": 104,
    "AU": 133,
    "GB": 148,
    "MX": 159
  }
}