{
  "summary": {
    "total_apps": 723,
    "total_countries": 7,
    "total_industries": 3,
    "avg_rating": 4.3,
    "last_updated": "2026-06-07T06:42:13.620277Z"
  },
  "top_movers": [
    {
      "app_id": "uk.co.credabilityapp",
      "country_code": "GB",
      "store": "google_play",
      "timestamp": "2026-06-07T06:42:13.612475Z",
      "rank": 19,
      "rating": 4.71,
      "reviews": 3542,
      "min_installs": 384148,
      "installs_str": "100,000+",
      "dau_estimate": 5762,
      "ad_spend_intensity": 27.4,
      "rank_change": 6,
      "rating_change": 0.0,
      "reviews_change": 5,
      "installs_change": 0,
      "installs_growth": 0.0,
      "dau_change": 0,
      "is_new": false,
      "app_name": "CredAbility - Credit Score",
      "icon_url": "https://play-lh.googleusercontent.com/UINZO1yiSTZ4hdRt1NKt_mGlXkaHhswYJLLRGRx0dye6LWOaZ6TVeMI5rZ2NFuh1Ffo",
      "developer": "CredAbility",
      "industry": "insurance",
      "industry_name": "保险",
      "country_name": "英国"
    },
    {
      "app_id": "com.creditkarma.mobile.international",
      "country_code": "GB",
      "store": "google_play",
      "timestamp": "2026-06-07T06:42:13.612475Z",
      "rank": 14,
      "rating": 4.73,
      "reviews": 94539,
      "min_installs": 3179150,
      "installs_str": "1,000,000+",
      "dau_estimate": 52455,
      "ad_spend_intensity": 33.3,
      "rank_change": 5,
      "rating_change": 0.0,
      "reviews_change": 10,
      "installs_change": 0,
      "installs_growth": 0.0,
      "dau_change": 0,
      "is_new": false,
      "app_name": "Credit Karma — Credit Score",
      "icon_url": "https://play-lh.googleusercontent.com/KRNM7xYQSAfW8F4A22usVpiceAde0AcvJum33k0gnOSnze7uvEtUHjC_blbUIctmb-Y",
      "developer": "Credit Karma, LLC",
      "industry": "credit",
      "industry_name": "信贷",
      "country_name": "英国"
    },
    {
      "app_id": "com.maybank.bankpublic.jpmorgan",
      "country_code": "MY",
      "store": "google_play",
      "timestamp": "2026-06-07T06:42:13.612475Z",
      "rank": 3,
      "rating": 4.4,
      "reviews": 692,
      "min_installs": 7187,
      "installs_str": "5,000+",
      "dau_estimate": 86,
      "ad_spend_intensity": 34.7,
      "rank_change": 4,
      "rating_change": 0.01,
      "reviews_change": 11,
      "installs_change": 0,
      "installs_growth": 0.0,
      "dau_change": 0,
      "is_new": false,
      "app_name": "SpeedyAid",
      "icon_url": "https://play-lh.googleusercontent.com/IlvYy4wK7vP-5rF-bjeS9Dtr4WnQOQDDwZqR_dSwAXmd1DCJENvSu8crRJCk1oUeVtb2oFV_OayIpIvdz2_8KA",
      "developer": "Powered by KHAZANA FINANCIAL SERVICES LIMITED",
      "industry": "credit",
      "industry_name": "信贷",
      "country_name": "马来西亚"
    },
    {
      "app_id": "directlending.bnpl.mobile",
      "country_code": "MY",
      "store": "google_play",
      "timestamp": "2026-06-07T06:42:13.612475Z",
      "rank": 13,
      "rating": null,
      "reviews": null,
      "min_installs": 1275,
      "installs_str": "1,000+",
      "dau_estimate": 8,
      "ad_spend_intensity": 39.3,
      "rank_change": 4,
      "rating_change": null,
      "reviews_change": 0,
      "installs_change": 0,
      "installs_growth": 0.0,
      "dau_change": 0,
      "is_new": false,
      "app_name": "Direct Lending - BNPL Malaysia",
      "icon_url": "https://play-lh.googleusercontent.com/v1EL9NWy7FayXVmoZKUeab57oXe3Nz9uzopIQ2xbzCHF_-GuZNC4m2JFAhgfZq6DxjM2djqgMTB5LD4Kow9djg",
      "developer": "Direct Lending",
      "industry": "credit",
      "industry_name": "信贷",
      "country_name": "马来西亚"
    },
    {
      "app_id": "com.eos_credit.eos_credit",
      "country_code": "MY",
      "store": "google_play",
      "timestamp": "2026-06-07T06:42:13.612475Z",
      "rank": 20,
      "rating": 1.89,
      "reviews": 18,
      "min_installs": 4392,
      "installs_str": "1,000+",
      "dau_estimate": 30,
      "ad_spend_intensity": 38.3,
      "rank_change": 4,
      "rating_change": 0.0,
      "reviews_change": 0,
      "installs_change": 0,
      "installs_growth": 0.0,
      "dau_change": 0,
      "is_new": false,
      "app_name": "EOS Credit",
      "icon_url": "https://play-lh.googleusercontent.com/RHV0GVtSm5R6pCUUU8x9OSRcyGzcB1HHlvHYLlYXHD7h-bc2UNuLIgy9i_3KqDvfTVg",
      "developer": "EOS Systems Sdn. Bhd.",
      "industry": "credit",
      "industry_name": "信贷",
      "country_name": "马来西亚"
    },
    {
      "app_id": "com.uk.mutual.mutualapp",
      "country_code": "GB",
      "store": "google_play",
      "timestamp": "2026-06-07T06:42:13.612475Z",
      "rank": 20,
      "rating": 4.4,
      "reviews": 5,
      "min_installs": 1558,
      "installs_str": "1,000+",
      "dau_estimate": 18,
      "ad_spend_intensity": 30.5,
      "rank_change": 4,
      "rating_change": 0.0,
      "reviews_change": 0,
      "installs_change": 0,
      "installs_growth": 0.0,
      "dau_change": 0,
      "is_new": false,
      "app_name": "Mutual Loans",
      "icon_url": "https://play-lh.googleusercontent.com/feJwSXzoOa6_8QpGV-9fvpevddxn-Pm1emi1FhUCkh0xMfuOriIWAwzJvYxYO-B_AA",
      "developer": "Mutual Development",
      "industry": "credit",
      "industry_name": "信贷",
      "country_name": "英国"
    },
    {
      "app_id": "com.untied.umiles",
      "country_code": "GB",
      "store": "google_play",
      "timestamp": "2026-06-07T06:42:13.612475Z",
      "rank": 25,
      "rating": 4.61,
      "reviews": 116,
      "min_installs": 4125,
      "installs_str": "1,000+",
      "dau_estimate": 61,
      "ad_spend_intensity": 24.4,
      "rank_change": 4,
      "rating_change": 0.0,
      "reviews_change": 1,
      "installs_change": 0,
      "installs_growth": 0.0,
      "dau_change": 0,
      "is_new": false,
      "app_name": "\"untied\" UK's personal tax app",
      "icon_url": "https://play-lh.googleusercontent.com/WY7ei2PcQAWgjabxIwUIOP3HqcTS--k_tg02BaJAd7xVuwr9JL4QIs2QiQ6jimybI_zyu6VoJaun-0vx_pEvkA",
      "developer": "untied",
      "industry": "finance",
      "industry_name": "理财",
      "country_name": "英国"
    },
    {
      "app_id": "ph.onlineloans.mobile.android",
      "country_code": "PH",
      "store": "google_play",
      "timestamp": "2026-06-07T06:42:13.612475Z",
      "rank": 23,
      "rating": 4.59,
      "reviews": 102630,
      "min_installs": 6410118,
      "installs_str": "5,000,000+",
      "dau_estimate": 124997,
      "ad_spend_intensity": 20.6,
      "rank_change": 3,
      "rating_change": 0.0,
      "reviews_change": 61,
      "installs_change": 3568,
      "installs_growth": 0.06,
      "dau_change": 70,
      "is_new": false,
      "app_name": "Online Loans Pilipinas",
      "icon_url": "https://play-lh.googleusercontent.com/-z1ecZViLFqx_Z-lEveJrkQuD4ykgAy3xGZkoK3wBl9zioZmvyLuGqQ_RJnLXn1lIQ",
      "developer": "ONLINE LOANS PILIPINAS FINANCING INC.",
      "industry": "credit",
      "industry_name": "信贷",
      "country_name": "菲律宾"
    },
    {
      "app_id": "com.officialgroup.duitgini",
      "country_code": "MY",
      "store": "google_play",
      "timestamp": "2026-06-07T06:42:13.612475Z",
      "rank": 11,
      "rating": 3.38,
      "reviews": 246,
      "min_installs": 93980,
      "installs_str": "50,000+",
      "dau_estimate": 657,
      "ad_spend_intensity": 28.2,
      "rank_change": 3,
      "rating_change": 0.03,
      "reviews_change": 4,
      "installs_change": 1102,
      "installs_growth": 1.19,
      "dau_change": 7,
      "is_new": false,
      "app_name": "DuitGini",
      "icon_url": "https://play-lh.googleusercontent.com/DPDNNX4RzqaDv_An3awvgd4pOF_qqvgTWCVy2Kc6ZPh0TNPhSHg3ZnyLlV4PrdxXiHs15Q9YgGg0DnG2GTIK",
      "developer": "Tapps.tech",
      "industry": "credit",
      "industry_name": "信贷",
      "country_name": "马来西亚"
    },
    {
      "app_id": "com.optipay.littlecash",
      "country_code": "AU",
      "store": "google_play",
      "timestamp": "2026-06-07T06:42:13.612475Z",
      "rank": 24,
      "rating": 4.26,
      "reviews": 104479,
      "min_installs": 1232328,
      "installs_str": "1,000,000+",
      "dau_estimate": 19224,
      "ad_spend_intensity": 20.3,
      "rank_change": 3,
      "rating_change": 0.01,
      "reviews_change": 21,
      "installs_change": 0,
      "installs_growth": 0.0,
      "dau_change": 0,
      "is_new": false,
      "app_name": "Little Cash - Mobile Loans",
      "icon_url": "https://play-lh.googleusercontent.com/2bCaBF1Lb5eJkhmZ9KNMg7ww-PEvyk7TXKfTxSr46_M1tLKhZeTPZJoq5EQ4NFa1c3g",
      "developer": "Optipay Limited",
      "industry": "credit",
      "industry_name": "信贷",
      "country_name": "英国"
    }
  ],
  "industry_distribution": {
    "credit": 432,
    "finance": 265,
    "insurance": 26
  },
  "country_distribution": {
    "PH": 61,
    "ID": 46,
    "PK": 97,
    "MY": 99,
    "AU": 129,
    "GB": 140,
    "MX": 151
  }
}